{"image":{"clarity":"normal","collectionId":0,"collectionName":"test","format":"jpg","hdfsFilename":null,"height":480,"id":"0ab092c536335ab2031cde69d39d68df","orientation":90,"orientationVerified":true,"rawFilePath":"","rawFilename":"image_1515387191011.ir.jpg","width":640},"objects":{"face":[{"id":"0872b0c5e3bc427fa7e735b36b2e7d2d","imageId":"0ab092c536335ab2031cde69d39d68df","position":{"bottom":462.73381294964031,"left":202.58992805755395,"right":331.51079136690646,"sourceQuality":"Labeled","top":330.74340527577937,"ts":"2018-04-27T21:25:32+08:00"},"schemaVersion":"0.1.0","typeId":1,"typeName":"face"}]}}